trsolver/__init__.py
trsolver/client.py
trsolver-0.1.2.dist-info/METADATA
trsolver-0.1.2.dist-info/WHEEL
trsolver-0.1.2.dist-info/top_level.txt
trsolver-0.1.2.dist-info/RECORD
