Metadata-Version: 2.4
Name: trsolver
Version: 0.1.2
Summary: Client library for the trsolver.com API
Author-email: MUHAMMED SAID KARAKOYUN <proxycin@gmail.com>
Project-URL: Homepage, https://github.com/LÜTFEN GÜNCELLEYİN/trsolver
Project-URL: Bug Tracker, https://github.com/LÜTFEN GÜNCELLEYİN/trsolver/issues
Classifier: Programming Language :: Python :: 3
Classifier: License :: OSI Approved :: MIT License
Classifier: Operating System :: OS Independent
Requires-Python: >=3.7
Requires-Dist: requests>=2.20
